LICENSE
MANIFEST.in
README.md
VERSION
setup.py
galru/Blast.py
galru/BlastDatabase.py
galru/BlastFilter.py
galru/BlastResult.py
galru/DatabaseBuilder.py
galru/Galru.py
galru/GalruCreateCas.py
galru/GalruCreateDatabase.py
galru/GalruCreateSpecies.py
galru/GalruShrinkDatabase.py
galru/GalruSpol.py
galru/Mlst.py
galru/Results.py
galru/Schemas.py
galru/__init__.py
galru.egg-info/PKG-INFO
galru.egg-info/SOURCES.txt
galru.egg-info/dependency_links.txt
galru.egg-info/requires.txt
galru.egg-info/top_level.txt
galru/data/Mycobacterium_tuberculosis/crispr_regions.fasta
galru/data/Mycobacterium_tuberculosis/metadata.tsv
galru/data/Mycobacterium_tuberculosis/spacers.fasta
scripts/galru
scripts/galru_create_database
scripts/galru_create_species
scripts/galru_shrink_database