Metadata-Version: 2.1
Name: galru
Version: 1.0.0
Summary: galru: CRISPR types
Home-page: https://github.com/quadram-institute-bioscience/galru
Author: Andrew J. Page
Author-email: andrew.page@quadram.ac.uk
License: GPLv3
Platform: UNKNOWN
Classifier: Development Status :: 4 - Beta
Classifier: Intended Audience :: Science/Research
Classifier: Topic :: Scientific/Engineering :: Bio-Informatics
Classifier: Programming Language :: Python :: 3 :: Only
Classifier: License :: OSI Approved :: GNU General Public License v3 (GPLv3)
